odoo8_addon_business_requirement_deliverable_report-8.0.5.0.2-py2.7-nspkg.pth
odoo8_addon_business_requirement_deliverable_report-8.0.5.0.2.dist-info/DESCRIPTION.rst
odoo8_addon_business_requirement_deliverable_report-8.0.5.0.2.dist-info/METADATA
odoo8_addon_business_requirement_deliverable_report-8.0.5.0.2.dist-info/RECORD
odoo8_addon_business_requirement_deliverable_report-8.0.5.0.2.dist-info/WHEEL
odoo8_addon_business_requirement_deliverable_report-8.0.5.0.2.dist-info/metadata.json
odoo8_addon_business_requirement_deliverable_report-8.0.5.0.2.dist-info/namespace_packages.txt
odoo8_addon_business_requirement_deliverable_report-8.0.5.0.2.dist-info/top_level.txt
odoo_addons/business_requirement_deliverable_report/README.rst
odoo_addons/business_requirement_deliverable_report/__init__.py
odoo_addons/business_requirement_deliverable_report/__openerp__.py
odoo_addons/business_requirement_deliverable_report/data/br_report_paperformat.xml
odoo_addons/business_requirement_deliverable_report/i18n/sl.po
odoo_addons/business_requirement_deliverable_report/report/report.xml
odoo_addons/business_requirement_deliverable_report/static/description/icon.png
odoo_addons/business_requirement_deliverable_report/static/img/bus_req_report1.png
odoo_addons/business_requirement_deliverable_report/static/img/bus_req_report2.png
odoo_addons/business_requirement_deliverable_report/static/img/bus_req_report3.png
odoo_addons/business_requirement_deliverable_report/views/report_business_requirement.xml
odoo_addons/business_requirement_deliverable_report/views/report_business_requirement_deliverable.xml
odoo_addons/business_requirement_deliverable_report/views/report_business_requirement_deliverable_resource.xml
