Metadata-Version: 2.0
Name: odoo8-addon-business-requirement-deliverable-report
Version: 8.0.5.0.2
Summary: Print the Business Requirement Document for your customers
Home-page: https://www.elico-corp.com
Author: Elico Corp, Odoo Community Association (OCA)
Author-email: support@odoo-community.org
License: AGPL-3
Platform: UNKNOWN
Classifier: Programming Language :: Python :: 2.7
Classifier: Framework :: Odoo
Classifier: License :: OSI Approved :: GNU Affero General Public License v3
Requires-Dist: odoo (<9.0a,>=8.0a)
Requires-Dist: odoo8-addon-business-requirement-deliverable
